<?xml version="1.0" encoding="windows-1250"?>
<HelpEditing xmlns:xsi="http://www.w3.org/2001/XMLSchema-instance" xmlns:xsd="http://www.w3.org/2001/XMLSchema">
  <HelpData>
    <HelpEntry item="Name">
      <Text>Name of the skill profile</Text>
    </HelpEntry>
    <HelpEntry item="Generate XP levels">
      <Text>Defines how many levels you want to generate</Text>
    </HelpEntry>
    <HelpEntry item="Base XP value">
      <Text>Defines experience value for the first level</Text>
    </HelpEntry>
    <HelpEntry item="Percentage XP/lev (%)">
      <Text>Defines additional percentage value for each of the generated levels</Text>
    </HelpEntry>
    <HelpEntry item="Generate levels">
      <Text>Generate levels based on specified parameters</Text>
    </HelpEntry>
    <HelpEntry item="Add XP level">
      <Text>Add one level at the end</Text>
    </HelpEntry>
    <HelpEntry item="Remove last level">
      <Text>Remove last level from the list</Text>
    </HelpEntry>
    <HelpEntry item="Hide Levels">
      <Text>Hide list</Text>
    </HelpEntry>
    <HelpEntry item="Add level diff">
      <Text>Defines experience reduction based on the level difference. For crafting skill it is level difference between crafted recipe and player skill level. For gathering skill it is difference between resource node level and player skill level. Combat doesn’t have this option.</Text>
    </HelpEntry>
  </HelpData>
</HelpEditing>